mdforce/__init__.py
mdforce/terms.py
mdforce/terms_iter.py
mdforce/terms_vectorized.py
mdforce/models/__init__.py
mdforce/models/water/__init__.py
mdforce/models/water/flexible_3site_spc/__init__.py
mdforce/models/water/flexible_3site_spc/_create_force_field.py
mdforce/models/water/flexible_3site_spc/_find_interacting_partners.py
mdforce/models/water/flexible_3site_spc/_read_params.py
mdforce-0.0.0.dist-info/LICENSE
mdforce-0.0.0.dist-info/METADATA
mdforce-0.0.0.dist-info/WHEEL
mdforce-0.0.0.dist-info/top_level.txt
mdforce-0.0.0.dist-info/RECORD
